{"/":{"title":"HimGK","content":"","lastmodified":"2022-08-17T16:01:44.974779192Z","tags":null},"/Himachal-Pradesh/":{"title":"Himachal Pradesh","content":"Lorem ipsum dolor sit, amet consectetur adipisicing elit. Natus nesciunt pariatur eos rem assumenda harum debitis et, eveniet doloribus voluptatem quam delectus officia impedit autem molestias repellat velit. Officia tenetur architecto sapiente nesciunt officiis, totam quod quam repudiandae magni exercitationem, iste itaque eius earum adipisci consequuntur hic voluptate expedita eligendi. Quo unde commodi quia repellat reiciendis natus tenetur ipsam odit obcaecati totam. Excepturi cupiditate inventore explicabo odio necessitatibus possimus exercitationem nemo officia est harum. Amet voluptatum delectus eaque eos, at optio labore mollitia a alias obcaecati repellendus sed soluta doloremque unde maxime aut voluptate illo voluptates accusamus officia dolores consectetur corrupti pariatur! Dicta fugit dolores aliquam tempora sunt iste fugiat, eos nihil quia possimus repellendus totam eaque veniam illo architecto maxime eum? Ipsam dolor perspiciatis aut quis necessitatibus facilis praesentium commodi quasi aspernatur voluptates ipsa autem maiores libero consectetur facere itaque illum voluptatum architecto eum dolore recusandae, quaerat veritatis! Aspernatur consequuntur alias, tempora sunt aperiam incidunt, maiores corrupti consequatur ut ullam placeat minus. Aliquam cupiditate debitis, ipsa sed iusto deserunt. Corporis, labore. Dolorum tenetur mollitia soluta expedita, adipisci libero itaque, illo eius nobis eos ipsum! Ut sit ad nostrum explicabo amet aperiam nisi ipsum tempore. Quam culpa vel sequi aspernatur eius iure dignissimos minima libero molestiae veniam? Perferendis, quod cupiditate? Laborum et veniam at incidunt dolorum, sit impedit dignissimos voluptatibus consequatur, ab natus aperiam quaerat ducimus temporibus fuga sunt molestias quo optio repudiandae suscipit vel. Voluptatem impedit, soluta reprehenderit quis laudantium doloremque quae perspiciatis labore iusto, vero culpa aperiam dolorem reiciendis debitis. Aut mollitia, magnam iste maiores eaque fugiat consectetur architecto, corrupti nulla, quibusdam provident esse incidunt ea iure velit error omnis ex labore voluptatem obcaecati animi aliquid quae fugit. Qui at unde tenetur velit laboriosam veritatis ipsam quasi obcaecati voluptas. Rerum ut, fugiat veritatis, necessitatibus cupiditate excepturi aut velit ullam sapiente quod, vitae saepe quo accusantium pariatur quibusdam quis quia deleniti reiciendis ipsam? Dolorem omnis facilis eligendi distinctio excepturi autem veniam, nesciunt asperiores laborum veritatis illo! Omnis fugiat expedita assumenda enim saepe, possimus, aliquid voluptatum laboriosam non et officia! Corrupti mollitia quasi reprehenderit, tempore non incidunt porro vel hic explicabo dolores provident officia illum qui dolor culpa sit? Minus natus debitis animi, laboriosam reiciendis iure enim ipsam quisquam vero veniam exercitationem officiis quia cupiditate eum ex modi quo vel dicta porro! Hic expedita eaque cumque, culpa illum optio modi mollitia ex adipisci deleniti! Suscipit mollitia saepe natus possimus? Perferendis culpa in quidem fugiat odit voluptas earum optio, ex cumque rerum reprehenderit ipsum necessitatibus, a sint id nesciunt doloribus! Dolorem deleniti voluptatibus nostrum placeat, voluptas ullam magnam magni! Iure alias maxime fugiat neque dolores quia sint aperiam illum quibusdam odio ea cum accusantium, asperiores optio, aliquam laboriosam consequatur cupiditate et consectetur autem maiores. Et expedita aut nostrum earum blanditiis modi rerum quo minima a, soluta recusandae ab officia possimus dolorum numquam quasi dignissimos ipsum ipsam quaerat. Quisquam commodi deleniti id ratione incidunt! Nemo beatae ducimus vero? At, delectus, sapiente eligendi natus aliquam blanditiis expedita fugiat commodi corporis nostrum quia itaque tempore culpa optio tempora? Reprehenderit eius inventore doloremque, nesciunt officia quidem, corporis, dolore labore blanditiis minima error perferendis tenetur repudiandae sint ipsam illo ad autem ex cum? Qui dicta minima voluptas nobis laboriosam fugiat, iste corrupti hic eligendi? Nam ab beatae veniam ullam quas? Natus itaque, enim totam ipsam mollitia repellendus? Fuga ea velit minima mollitia reiciendis eius doloremque, adipisci, praesentium facilis unde repudiandae impedit pariatur nostrum inventore odit fugit in ipsam ut cum! Ex, officia eius? Et molestiae cupiditate facilis officiis voluptatem aliquid reiciendis voluptates quisquam quo soluta pariatur repudiandae quaerat minus iste, totam neque dolorem numquam asperiores. Cum.","lastmodified":"2022-08-17T16:01:44.974779192Z","tags":null},"/Himachal-Pradesh/Districts/":{"title":"Districts of Himachal Pradesh","content":"* Lorem ipsum dolor sit amet consectetur adipisicing elit. Voluptatem explicabo expedita sunt accusamus ad consequatur mollitia obcaecati. Rerum, exercitationem dolore odio, quas ipsa ullam fuga incidunt repudiandae doloribus magnam deleniti.","lastmodified":"2022-08-17T16:01:44.974779192Z","tags":null},"/Himachal-Pradesh/Districts/Bilaspur/":{"title":"Bilaspur District","content":"* This section have notes on bilaspur","lastmodified":"2022-08-17T16:01:44.974779192Z","tags":null},"/Himachal-Pradesh/Districts/Bilaspur/History-of-Bilaspur":{"title":"History of Bilaspur","content":"* Lorem ipsum dolor sit amet, consectetur adipisicing elit. Aut at ratione cum rerum odio. Veritatis, nesciunt eum deleniti voluptates quaerat animi! Vero, nobis facere quam reprehenderit voluptates odit. Quaerat repellendus quisquam, maiores dolores, pariatur optio dolorem ea beatae repudiandae necessitatibus, reiciendis quod. Repellat fugiat libero deserunt totam quae necessitatibus officiis modi doloremque omnis, asperiores hic nostrum minus nihil architecto vero repudiandae atque dicta aliquam molestiae! Magni, eius at. Magni, officia error. Vitae, voluptate, adipisci praesentium molestias possimus mollitia quae iure aspernatur quaerat rerum eaque dicta totam dolorem, odit modi. Omnis, ducimus autem. Sunt assumenda sed error velit quae fuga magnam voluptate ullam nulla exercitationem iste qui commodi ipsam id perspiciatis iure, porro aliquam libero corporis, vero cupiditate! Ullam nisi nesciunt veniam reiciendis cumque. Odio temporibus explicabo laudantium quidem quisquam consequatur reprehenderit minus voluptatem magnam magni aliquam ea iusto veritatis rem, eius distinctio dignissimos molestias sequi. Similique laboriosam laudantium, unde quisquam placeat neque vel aperiam aliquid ut quidem provident cupiditate possimus vitae molestiae expedita nihil, architecto dolor eius! Neque, recusandae repellendus fugit soluta accusantium quidem iusto earum magni vero qui laborum omnis debitis eius, vel corrupti ea praesentium ipsam autem doloribus ad accusamus? Quia a dolores veritatis odio aspernatur reiciendis magnam nobis mollitia vitae impedit, rerum amet deserunt qui earum hic molestias doloremque officia nemo quo quasi delectus iste rem. Ad qui quibusdam alias quas nobis quae perspiciatis magnam officia incidunt exercitationem facilis, hic ex. Molestias quis tempora voluptas consequatur neque nam quas delectus officiis odio corporis eum iure cumque, tenetur repellendus optio cum totam dolore est aliquid reprehenderit alias! Officiis perspiciatis accusantium, tempore molestiae omnis libero! Aperiam quaerat ullam impedit, animi vel dolore esse consequuntur ducimus delectus perferendis est libero vitae doloribus repellat voluptatem dolores beatae! Natus provident dolorem eos cupiditate doloremque illum molestiae vel porro tempora sunt corrupti praesentium repellendus dolorum architecto ipsum culpa cum laboriosam, possimus modi nam accusantium qui quidem voluptates et! Libero incidunt ducimus animi voluptas dignissimos, nihil ad doloribus expedita excepturi odio consequatur assumenda obcaecati repellat tempore eos atque commodi quibusdam eum officia omnis. Magnam perferendis doloribus adipisci dolore sapiente, libero accusantium iste deserunt mollitia dolorem odit obcaecati eveniet rerum accusamus incidunt ab, voluptates, commodi nihil distinctio iure! Ratione consequuntur fugit libero ipsum voluptate nobis. Praesentium blanditiis et cum voluptate exercitationem pariatur ipsum quod doloremque odio consectetur quasi recusandae earum facilis consequuntur molestiae accusantium repellendus fugiat, maiores possimus. Non possimus rerum id enim corporis quibusdam suscipit facere eius ratione inventore omnis, nemo temporibus perferendis et nihil atque sequi voluptatem nam illo qui exercitationem aliquam! In blanditiis magni expedita aliquam, quam molestiae veritatis dolores aspernatur omnis neque dolore doloremque ducimus sapiente? Delectus modi dolor nisi commodi illum, dolorem optio, aperiam consectetur blanditiis assumenda maxime culpa provident, expedita veniam officia autem! Ex alias veritatis officiis doloribus autem necessitatibus accusantium rem quidem velit enim, libero quibusdam consequuntur voluptatibus eligendi exercitationem fugiat quas? Aut error similique excepturi nisi, numquam molestiae amet, optio voluptas temporibus voluptates harum laborum aperiam soluta veritatis incidunt autem dicta. Id ut sed culpa doloribus quasi.","lastmodified":"2022-08-17T16:01:44.974779192Z","tags":null},"/Himachal-Pradesh/Districts/Test/":{"title":"Test","content":"","lastmodified":"2022-08-17T16:01:44.974779192Z","tags":null},"/Himachal-Pradesh/Pradesh/":{"title":"Pradesh","content":"","lastmodified":"2022-08-17T16:01:44.974779192Z","tags":null}}